Workbook

Sheet Enunciado
A1: EDJAI ACADEMIC | PROJECTO FINAL DE EXCEL
A3: TEMA | B3: Análise de desempenho comercial e KPIs de vendas
A4: CONTEXTO | B4: Assuma a função de Técnico de Vendas da empresa fictícia Kwanza Comercial, que comercializa equipamentos e material de escritório em Angola.
A5: BASE DE DADOS | B5: 600 registos totalmente sintéticos, de Janeiro a Dezembro de 2025. Nenhum cliente ou resultado representa uma entidade real.
A6: MISSÃO | B6: Transformar os registos de vendas em informação de gestão e apresentar um dashboard interactivo para a Direcção Comercial.
A7: ETAPA 1 | PREPARAÇÃO | B7: Verificar tipos de dados, datas, duplicados, consistência de preços, quantidades, custos, descontos e estados. Não alterar os dados originais sem justificação.
A8: ETAPA 2 | CÁLCULOS | B8: Criar colunas auxiliares para mês, trimestre, receita bruta, desconto em Kz, receita líquida, custo total, lucro bruto e margem bruta. Contabilizar facturação apenas para negócios Ganhos.
A9: ETAPA 3 | KPIs | B9: Calcular: receita líquida; vendas ganhas; unidades vendidas; ticket médio; lucro bruto; margem bruta; taxa de conversão; taxa de desconto; cumprimento da meta; variação mensal; vendas por vendedor, categoria, canal e província.
A10: ETAPA 4 | ANÁLISE | B10: Construir tabelas dinâmicas por mês, vendedor, província, canal e categoria. Comparar receita realizada com as metas mensais e analisar os desvios.
A11: ETAPA 5 | DASHBOARD | B11: Criar painel com cartões KPI, evolução mensal, ranking dos vendedores, receita por categoria, vendas por província e filtros/segmentações por mês, vendedor, canal e estado.
A12: ETAPA 6 | DECISÕES | B12: Apresentar pelo menos 5 conclusões fundamentadas em números e 5 recomendações comerciais concretas.
A13: ENTREGÁVEIS | B13: Ficheiro Excel final com base tratada, cálculos, tabelas dinâmicas, dashboard e folha de conclusões. Apresentação oral de 8 a 12 minutos.
A14: CRITÉRIOS DE AVALIAÇÃO | B14: Qualidade e consistência dos dados 15%; fórmulas e KPIs 30%; tabelas dinâmicas 20%; dashboard 25%; interpretação e recomendações 10%.
... A16: FÓRMULAS SUGERIDAS | B16: SOMASES, CONT.SES, SE, SEERRO, SOMA, MÉDIA, MÊS, ANO e tabelas dinâmicas. Pode usar equivalentes em inglês conforme a versão do Excel.

Sheet Base_Vendas
A1: ID_Oportunidade | B1: Data | C1: Vendedor | D1: Provincia | E1: Canal | F1: Cliente_Ficticio | G1: Categoria | H1: Produto | I1: Quantidade | J1: Preco_Unitario_Kz | K1: Custo_Unitario_Kz | L1: Desconto_Pct | M1: Estado | N1: Origem_Lead | O1: Mes | P1: Trimestre | Q1: Receita_Bruta_Kz | R1: Desconto_Kz | S1: Receita_Liquida_Kz | T1: Custo_Total_Kz | U1: Lucro_Bruto_Kz | V1: Margem_Bruta_Pct
A2: OP-0001 | B2: 45928 | C2: Ana Manuel | D2: Cabinda | E2: Telefone | F2: Cliente Simulado 034 | G2: Escritório | H2: Secretária de escritório | I2: 1 | J2: 138000 | K2: 99000 | L2: 0.12 | M2: Ganho | N2: Cliente recorrente | O2: =MONTH(B2) -> 9 | P2: =ROUNDUP(O2/3,0) -> 3 | Q2: =I2*J2 -> 138000 | R2: =Q2*L2 -> 16560 | S2: =IF(M2="Ganho",Q2-R2,0) -> 121440 | T2: =IF(M2="Ganho",I2*K2,0) -> 99000 | U2: =S2-T2 -> 22440 | V2: =IFERROR(U2/S2,0) -> 0.18478261
A3: OP-0002 | B3: 45814 | C3: Carla Domingos | D3: Luanda | E3: Telefone | F3: Cliente Simulado 001 | G3: Escritório | H3: Secretária de escritório | I3: 2 | J3: 138000 | K3: 99000 | L3: 0.08 | M3: Ganho | N3: Redes sociais | O3: =MONTH(B3) -> 6 | P3: =ROUNDUP(O3/3,0) -> 2 | Q3: =I3*J3 -> 276000 | R3: =Q3*L3 -> 22080 | S3: =IF(M3="Ganho",Q3-R3,0) -> 253920 | T3: =IF(M3="Ganho",I3*K3,0) -> 198000 | U3: =S3-T3 -> 55920 | V3: =IFERROR(U3/S3,0) -> 0.22022684
A4: OP-0003 | B4: 45926 | C4: Ana Manuel | D4: Huambo | E4: WhatsApp | F4: Cliente Simulado 159 | G4: Informática | H4: Monitor 24 polegadas | I4: 1 | J4: 115000 | K4: 82000 | L4: 0.03 | M4: Ganho | N4: Prospecção | O4: =MONTH(B4) -> 9 | P4: =ROUNDUP(O4/3,0) -> 3 | Q4: =I4*J4 -> 115000 | R4: =Q4*L4 -> 3450 | S4: =IF(M4="Ganho",Q4-R4,0) -> 111550 | T4: =IF(M4="Ganho",I4*K4,0) -> 82000 | U4: =S4-T4 -> 29550 | V4: =IFERROR(U4/S4,0) -> 0.26490363
A5: OP-0004 | B5: 45853 | C5: Carla Domingos | D5: Benguela | E5: Website | F5: Cliente Simulado 201 | G5: Escritório | H5: Secretária de escritório | I5: 4 | J5: 138000 | K5: 99000 | L5: 0 | M5: Ganho | N5: Campanha digital | O5: =MONTH(B5) -> 7 | P5: =ROUNDUP(O5/3,0) -> 3 | Q5: =I5*J5 -> 552000 | R5: =Q5*L5 -> 0 | S5: =IF(M5="Ganho",Q5-R5,0) -> 552000 | T5: =IF(M5="Ganho",I5*K5,0) -> 396000 | U5: =S5-T5 -> 156000 | V5: =IFERROR(U5/S5,0) -> 0.2826087
A6: OP-0005 | B6: 45875 | C6: Bruno Costa | D6: Huambo | E6: Telefone | F6: Cliente Simulado 213 | G6: Informática | H6: Teclado e rato | I6: 4 | J6: 19000 | K6: 11500 | L6: 0.1 | M6: Perdido | N6: Recomendação | O6: =MONTH(B6) -> 8 | P6: =ROUNDUP(O6/3,0) -> 3 | Q6: =I6*J6 -> 76000 | R6: =Q6*L6 -> 7600 | S6: =IF(M6="Ganho",Q6-R6,0) -> 0 | T6: =IF(M6="Ganho",I6*K6,0) -> 0 | U6: =S6-T6 -> 0 | V6: =IFERROR(U6/S6,0) -> 0
A7: OP-0006 | B7: 45955 | C7: Filipe Afonso | D7: Luanda | E7: Loja | F7: Cliente Simulado 267 | G7: Escritório | H7: Cadeira ergonómica | I7: 4 | J7: 92000 | K7: 60000 | L7: 0.12 | M7: Ganho | N7: Cliente recorrente | O7: =MONTH(B7) -> 10 | P7: =ROUNDUP(O7/3,0) -> 4 | Q7: =I7*J7 -> 368000 | R7: =Q7*L7 -> 44160 | S7: =IF(M7="Ganho",Q7-R7,0) -> 323840 | T7: =IF(M7="Ganho",I7*K7,0) -> 240000 | U7: =S7-T7 -> 83840 | V7: =IFERROR(U7/S7,0) -> 0.25889328
A8: OP-0007 | B8: 45873 | C8: Carla Domingos | D8: Luanda | E8: Telefone | F8: Cliente Simulado 160 | G8: Consumíveis | H8: Resma A4 | I8: 6 | J8: 5900 | K8: 3700 | L8: 0 | M8: Ganho | N8: Recomendação | O8: =MONTH(B8) -> 8 | P8: =ROUNDUP(O8/3,0) -> 3 | Q8: =I8*J8 -> 35400 | R8: =Q8*L8 -> 0 | S8: =IF(M8="Ganho",Q8-R8,0) -> 35400 | T8: =IF(M8="Ganho",I8*K8,0) -> 22200 | U8: =S8-T8 -> 13200 | V8: =IFERROR(U8/S8,0) -> 0.37288136
A9: OP-0008 | B9: 45811 | C9: Graça Miguel | D9: Cuanza Sul | E9: Visita comercial | F9: Cliente Simulado 159 | G9: Consumíveis | H9: Toner compatível | I9: 2 | J9: 32000 | K9: 21000 | L9: 0.08 | M9: Ganho | N9: Campanha digital | O9: =MONTH(B9) -> 6 | P9: =ROUNDUP(O9/3,0) -> 2 | Q9: =I9*J9 -> 64000 | R9: =Q9*L9 -> 5120 | S9: =IF(M9="Ganho",Q9-R9,0) -> 58880 | T9: =IF(M9="Ganho",I9*K9,0) -> 42000 | U9: =S9-T9 -> 16880 | V9: =IFERROR(U9/S9,0) -> 0.28668478
A10: OP-0009 | B10: 45839 | C10: Ana Manuel | D10: Luanda | E10: Telefone | F10: Cliente Simulado 089 | G10: Consumíveis | H10: Kit de papelaria | I10: 8 | J10: 16500 | K10: 10000 | L10: 0 | M10: Ganho | N10: Redes sociais | O10: =MONTH(B10) -> 7 | P10: =ROUNDUP(O10/3,0) -> 3 | Q10: =I10*J10 -> 132000 | R10: =Q10*L10 -> 0 | S10: =IF(M10="Ganho",Q10-R10,0) -> 132000 | T10: =IF(M10="Ganho",I10*K10,0) -> 80000 | U10: =S10-T10 -> 52000 | V10: =IFERROR(U10/S10,0) -> 0.39393939
A11: OP-0010 | B11: 45870 | C11: Ana Manuel | D11: Cuanza Sul | E11: Website | F11: Cliente Simulado 134 | G11: Escritório | H11: Secretária de escritório | I11: 8 | J11: 138000 | K11: 99000 | L11: 0.03 | M11: Perdido | N11: Campanha digital | O11: =MONTH(B11) -> 8 | P11: =ROUNDUP(O11/3,0) -> 3 | Q11: =I11*J11 -> 1104000 | R11: =Q11*L11 -> 33120 | S11: =IF(M11="Ganho",Q11-R11,0) -> 0 | T11: =IF(M11="Ganho",I11*K11,0) -> 0 | U11: =S11-T11 -> 0 | V11: =IFERROR(U11/S11,0) -> 0
A12: OP-0011 | B12: 45930 | C12: Elsa Joaquim | D12: Cuanza Sul | E12: Website | F12: Cliente Simulado 235 | G12: Informática | H12: Portátil empresarial | I12: 3 | J12: 320000 | K12: 244000 | L12: 0.03 | M12: Ganho | N12: Redes sociais | O12: =MONTH(B12) -> 9 | P12: =ROUNDUP(O12/3,0) -> 3 | Q12: =I12*J12 -> 960000 | R12: =Q12*L12 -> 28800 | S12: =IF(M12="Ganho",Q12-R12,0) -> 931200 | T12: =IF(M12="Ganho",I12*K12,0) -> 732000 | U12: =S12-T12 -> 199200 | V12: =IFERROR(U12/S12,0) -> 0.21391753
A13: OP-0012 | B13: 45786 | C13: Filipe Afonso | D13: Huíla | E13: Visita comercial | F13: Cliente Simulado 076 | G13: Informática | H13: Impressora multifunções | I13: 8 | J13: 175000 | K13: 129000 | L13: 0 | M13: Em negociação | N13: Recomendação | O13: =MONTH(B13) -> 5 | P13: =ROUNDUP(O13/3,0) -> 2 | Q13: =I13*J13 -> 1400000 | R13: =Q13*L13 -> 0 | S13: =IF(M13="Ganho",Q13-R13,0) -> 0 | T13: =IF(M13="Ganho",I13*K13,0) -> 0 | U13: =S13-T13 -> 0 | V13: =IFERROR(U13/S13,0) -> 0
... A601: OP-0600 | B601: 45987 | C601: Bruno Costa | D601: Huambo | E601: Telefone | F601: Cliente Simulado 019 | G601: Consumíveis | H601: Toner compatível | I601: 7 | J601: 32000 | K601: 21000 | L601: 0 | M601: Ganho | N601: Recomendação | O601: =MONTH(B601) -> 11 | P601: =ROUNDUP(O601/3,0) -> 4 | Q601: =I601*J601 -> 224000 | R601: =Q601*L601 -> 0 | S601: =IF(M601="Ganho",Q601-R601,0) -> 224000 | T601: =IF(M601="Ganho",I601*K601,0) -> 147000 | U601: =S601-T601 -> 77000 | V601: =IFERROR(U601/S601,0) -> 0.34375

Sheet Metas
A1: METAS COMERCIAIS | 2025 (SINTÉTICAS)
A3: Mês | B3: Meta_Receita_Kz | C3: Receita_Realizada_Kz | D3: Cumprimento_Pct | E3: Desvio_Kz
A4: 1 | B4: 16000000 | C4: =SUMIF(Base_Vendas!$O$2:$O$601,A4,Base_Vendas!$S$2:$S$601) -> 16665223 | D4: =IFERROR(C4/B4,0) -> 1.0415764 | E4: =C4-B4 -> 665223
A5: 2 | B5: 16500000 | C5: =SUMIF(Base_Vendas!$O$2:$O$601,A5,Base_Vendas!$S$2:$S$601) -> 13995946 | D5: =IFERROR(C5/B5,0) -> 0.84823915 | E5: =C5-B5 -> -2504054
A6: 3 | B6: 18000000 | C6: =SUMIF(Base_Vendas!$O$2:$O$601,A6,Base_Vendas!$S$2:$S$601) -> 14582310 | D6: =IFERROR(C6/B6,0) -> 0.81012833 | E6: =C6-B6 -> -3417690
A7: 4 | B7: 18000000 | C7: =SUMIF(Base_Vendas!$O$2:$O$601,A7,Base_Vendas!$S$2:$S$601) -> 14525823 | D7: =IFERROR(C7/B7,0) -> 0.80699017 | E7: =C7-B7 -> -3474177
A8: 5 | B8: 19000000 | C8: =SUMIF(Base_Vendas!$O$2:$O$601,A8,Base_Vendas!$S$2:$S$601) -> 9597740 | D8: =IFERROR(C8/B8,0) -> 0.50514421 | E8: =C8-B8 -> -9402260
A9: 6 | B9: 17000000 | C9: =SUMIF(Base_Vendas!$O$2:$O$601,A9,Base_Vendas!$S$2:$S$601) -> 12004764 | D9: =IFERROR(C9/B9,0) -> 0.70616259 | E9: =C9-B9 -> -4995236
A10: 7 | B10: 18000000 | C10: =SUMIF(Base_Vendas!$O$2:$O$601,A10,Base_Vendas!$S$2:$S$601) -> 13976404 | D10: =IFERROR(C10/B10,0) -> 0.77646689 | E10: =C10-B10 -> -4023596
A11: 8 | B11: 19000000 | C11: =SUMIF(Base_Vendas!$O$2:$O$601,A11,Base_Vendas!$S$2:$S$601) -> 15764706 | D11: =IFERROR(C11/B11,0) -> 0.82972137 | E11: =C11-B11 -> -3235294
A12: 9 | B12: 19000000 | C12: =SUMIF(Base_Vendas!$O$2:$O$601,A12,Base_Vendas!$S$2:$S$601) -> 10649043 | D12: =IFERROR(C12/B12,0) -> 0.56047595 | E12: =C12-B12 -> -8350957
A13: 10 | B13: 13500000 | C13: =SUMIF(Base_Vendas!$O$2:$O$601,A13,Base_Vendas!$S$2:$S$601) -> 13958937 | D13: =IFERROR(C13/B13,0) -> 1.0339953 | E13: =C13-B13 -> 458937
A14: 11 | B14: 19000000 | C14: =SUMIF(Base_Vendas!$O$2:$O$601,A14,Base_Vendas!$S$2:$S$601) -> 11237946 | D14: =IFERROR(C14/B14,0) -> 0.59147084 | E14: =C14-B14 -> -7762054
A15: 12 | B15: 19500000 | C15: =SUMIF(Base_Vendas!$O$2:$O$601,A15,Base_Vendas!$S$2:$S$601) -> 12684684 | D15: =IFERROR(C15/B15,0) -> 0.65049662 | E15: =C15-B15 -> -6815316

Sheet Dashboard_Modelo
A1: PAINEL DE REFERÊNCIA | KPIs COMERCIAIS
D3: Mês | E3: Receita líquida | F3: Meta
A4: Receita líquida (Kz) | B4: =SUM(Base_Vendas!S2:S601) -> 159643526 | D4: =Metas!A4 -> 1 | E4: =Metas!C4 -> 16665223 | F4: =Metas!B4 -> 16000000
A5: Negócios ganhos | B5: =COUNTIF(Base_Vendas!M2:M601,"Ganho") -> 406 | D5: =Metas!A5 -> 2 | E5: =Metas!C5 -> 13995946 | F5: =Metas!B5 -> 16500000
A6: Unidades vendidas | B6: =SUMIF(Base_Vendas!M2:M601,"Ganho",Base_Vendas!I2:I601) -> 1749 | D6: =Metas!A6 -> 3 | E6: =Metas!C6 -> 14582310 | F6: =Metas!B6 -> 18000000
A7: Ticket médio (Kz) | B7: =IFERROR(B4/B5,0) -> 393210.66 | D7: =Metas!A7 -> 4 | E7: =Metas!C7 -> 14525823 | F7: =Metas!B7 -> 18000000
A8: Lucro bruto (Kz) | B8: =SUM(Base_Vendas!U2:U601) -> 37694326 | D8: =Metas!A8 -> 5 | E8: =Metas!C8 -> 9597740 | F8: =Metas!B8 -> 19000000
A9: Margem bruta | B9: =IFERROR(B8/B4,0) -> 0.23611559 | D9: =Metas!A9 -> 6 | E9: =Metas!C9 -> 12004764 | F9: =Metas!B9 -> 17000000
A10: Taxa de conversão | B10: =IFERROR(B5/COUNTA(Base_Vendas!A2:A601),0) -> 0.67666667 | D10: =Metas!A10 -> 7 | E10: =Metas!C10 -> 13976404 | F10: =Metas!B10 -> 18000000
A11: Desconto médio ponderado | B11: =IFERROR(SUMIF(Base_Vendas!M2:M601,"Ganho",Base_Vendas!R2:R601)/SUMIF(Base_Vendas!M2:M601,"Ganho",Base_Vendas!Q2:Q601),0) -> 0.058657892 | D11: =Metas!A11 -> 8 | E11: =Metas!C11 -> 15764706 | F11: =Metas!B11 -> 19000000
A12: Cumprimento anual da meta | B12: =IFERROR(B4/SUM(Metas!B4:B15),0) -> 0.75126365 | D12: =Metas!A12 -> 9 | E12: =Metas!C12 -> 10649043 | F12: =Metas!B12 -> 19000000
D13: =Metas!A13 -> 10 | E13: =Metas!C13 -> 13958937 | F13: =Metas!B13 -> 13500000
D14: =Metas!A14 -> 11 | E14: =Metas!C14 -> 11237946 | F14: =Metas!B14 -> 19000000
A15: DESAFIO: recriar e expandir este painel com tabelas dinâmicas, gráficos e segmentações. | D15: =Metas!A15 -> 12 | E15: =Metas!C15 -> 12684684 | F15: =Metas!B15 -> 19500000

Sheet Dicionario
A1: DICIONÁRIO DE DADOS E REGRAS
A3: Campo / KPI | B3: Definição | C3: Tipo | D3: Observações
A4: ID_Oportunidade | B4: Identificador único de cada oportunidade | C4: Texto | D4: 600 oportunidades, incluindo as não concluídas
A5: Data | B5: Data de registo da oportunidade | C5: Data | D5: Ano 2025
A6: Vendedor | B6: Responsável comercial | C6: Texto | D6: Nomes fictícios
A7: Provincia | B7: Província da operação | C7: Texto | D7: Contexto Angola
A8: Canal | B8: Canal de contacto comercial | C8: Texto | D8: Loja, WhatsApp, Telefone, Visita, Website
A9: Cliente_Ficticio | B9: Identificação anonimizada e inventada | C9: Texto | D9: Pode repetir-se
A10: Categoria / Produto | B10: Artigo comercializado | C10: Texto | D10: Catálogo fictício
A11: Quantidade | B11: Unidades por oportunidade | C11: Número | D11: Só contar como vendidas se Ganho
A12: Preco_Unitario_Kz | B12: Preço unitário antes do desconto | C12: Kz | D12: Valor inventado
A13: Custo_Unitario_Kz | B13: Custo unitário estimado | C13: Kz | D13: Valor inventado
A14: Desconto_Pct | B14: Percentagem de desconto | C14: Percentagem | D14: Aplica-se sobre receita bruta
... A20: Cumprimento da meta | B20: Receita líquida / meta mensal | C20: Percentagem | D20: Metas fictícias por mês
